idem_data_insights/conf.py
idem_data_insights/scripts.py
idem_data_insights/version.py
idem_data_insights/idem_data_insights/analyze.py
idem_data_insights/idem_data_insights/build.py
idem_data_insights/idem_data_insights/compiler.py
idem_data_insights/idem_data_insights/group.py
idem_data_insights/idem_data_insights/group_format.py
idem_data_insights/idem_data_insights/high.py
idem_data_insights/idem_data_insights/init.py
idem_data_insights/idem_data_insights/low.py
idem_data_insights/idem_data_insights/okey.py
idem_data_insights/idem_data_insights/rpath.py
idem_data_insights/idem_data_insights/template.py
idem_data_insights/idem_data_insights/wiz.py
idem_data_insights-1.0.2.dist-info/LICENSE
idem_data_insights-1.0.2.dist-info/METADATA
idem_data_insights-1.0.2.dist-info/WHEEL
idem_data_insights-1.0.2.dist-info/entry_points.txt
idem_data_insights-1.0.2.dist-info/top_level.txt
idem_data_insights-1.0.2.dist-info/RECORD
