Metadata-Version: 2.1
Name: idem-data-insights
Version: 1.0.2
Summary: UNKNOWN
Home-page: https://gitlab.com/vmware/idem/idem-data-insights
Author: Thomas S Hatch
Author-email: thatch45@gmail.com
License: UNKNOWN
Platform: UNKNOWN
Classifier: Environment :: Console
Classifier: Intended Audience :: Developers
Classifier: Intended Audience :: Information Technology
Classifier: Intended Audience :: System Administrators
Classifier: Operating System :: OS Independent
Classifier: Programming Language :: Python
Classifier: Programming Language :: Python :: 3.6
Classifier: Programming Language :: Python :: 3.7
Classifier: Programming Language :: Python :: 3.8
Classifier: Programming Language :: Python :: 3.9
Classifier: Development Status :: 5 - Production/Stable
Requires-Python: >=3.6
License-File: LICENSE
Requires-Dist: pop (>=22.0.1)
Requires-Dist: idem (>=19.4.2)
Requires-Dist: pandas
Requires-Dist: Jinja2
